falcon_sqla/__init__.py
falcon_sqla/constants.py
falcon_sqla/manager.py
falcon_sqla/middleware.py
falcon_sqla/session.py
falcon_sqla/util.py
falcon_sqla/version.py
falcon_sqla-0.5.0.dist-info/licenses/LICENSE
falcon_sqla-0.5.0.dist-info/METADATA
falcon_sqla-0.5.0.dist-info/WHEEL
falcon_sqla-0.5.0.dist-info/top_level.txt
falcon_sqla-0.5.0.dist-info/RECORD
