Metadata-Version: 2.4
Name: falcon-sqla
Version: 0.5.0
Summary: Middleware for integrating Falcon applications with SQLAlchemy.
Author-email: Vytautas Liuolia <vytautas.liuolia@gmail.com>
License: Apache 2.0
Project-URL: Homepage, https://github.com/vytas7/falcon-sqla
Project-URL: Documentation, https://falcon-sqla.readthedocs.io/
Project-URL: Source, https://github.com/vytas7/falcon-sqla
Project-URL: Funding, https://opencollective.com/falcon
Project-URL: Chat, https://gitter.im/falconry/user
Keywords: falcon,wsgi,database,middleware,orm,sqlalchemy
Classifier: Development Status :: 4 - Beta
Classifier: Environment :: Web Environment
Classifier: Intended Audience :: Developers
Classifier: License :: OSI Approved :: Apache Software License
Classifier: Natural Language :: English
Classifier: Operating System :: OS Independent
Classifier: Topic :: Database :: Front-Ends
Classifier: Topic :: Software Development :: Libraries :: Application Frameworks
Classifier: Programming Language :: Python
Classifier: Programming Language :: Python :: Implementation :: CPython
Classifier: Programming Language :: Python :: Implementation :: PyPy
Classifier: Programming Language :: Python :: 3
Classifier: Programming Language :: Python :: 3.9
Classifier: Programming Language :: Python :: 3.10
Classifier: Programming Language :: Python :: 3.11
Classifier: Programming Language :: Python :: 3.10
Classifier: Programming Language :: Python :: 3.11
Classifier: Programming Language :: Python :: 3.12
Classifier: Programming Language :: Python :: 3.13
Requires-Python: >=3.8
License-File: LICENSE
Requires-Dist: falcon>=3.0.0
Requires-Dist: SQLAlchemy>=2.0.0
Provides-Extra: docs
Requires-Dist: Sphinx; extra == "docs"
Requires-Dist: sphinx-rtd-theme; extra == "docs"
Provides-Extra: test
Requires-Dist: pytest; extra == "test"
Requires-Dist: pytest-cov; extra == "test"
Dynamic: license-file
